corehr_pdf_split/__init__.py
corehr_pdf_split/__main__.py
corehr_pdf_split/main.py
corehr_pdf_split-1.0.3.dist-info/METADATA
corehr_pdf_split-1.0.3.dist-info/WHEEL
corehr_pdf_split-1.0.3.dist-info/entry_points.txt
corehr_pdf_split-1.0.3.dist-info/licenses/LICENSE
corehr_pdf_split-1.0.3.dist-info/RECORD
