Metadata-Version: 2.4
Name: corehr-pdf-split
Version: 1.0.3
Summary: Split a CoreHR PDF application pack into multiple individual PDF applications.
Project-URL: Homepage, https://github.com/synthetic-society/corehr-pdf-split
Project-URL: Repository, https://github.com/synthetic-society/corehr-pdf-split
Project-URL: Issues, https://github.com/synthetic-society/corehr-pdf-split/issues
Author-email: Luc Rocher <luc@rocher.lc>
License: MIT
License-File: LICENSE
Keywords: applications,corehr,pdf,split
Classifier: Development Status :: 5 - Production/Stable
Classifier: Intended Audience :: End Users/Desktop
Classifier: License :: OSI Approved :: MIT License
Classifier: Programming Language :: Python :: 3.10
Classifier: Programming Language :: Python :: 3.11
Classifier: Programming Language :: Python :: 3.12
Classifier: Topic :: Office/Business
Classifier: Topic :: Utilities
Requires-Python: >=3.10
Requires-Dist: click>=8.1.7
Requires-Dist: pypdf2>=3.0.1
Provides-Extra: test
Requires-Dist: pytest>=7.0.0; extra == 'test'
Requires-Dist: reportlab>=4.0.0; extra == 'test'
